schema_registry
