Metadata-Version: 2.1
Name: sumup-sr-client
Version: 0.4.0
Summary: A Python Package for the sumup schema registry client
Home-page: UNKNOWN
Author: Ajay Muppuri
Author-email: ajay.muppuri@sumup.com
License: UNKNOWN
Platform: UNKNOWN
